LICENSE
MANIFEST.in
README.rst
requirements.txt
setup.py
py_roku.egg-info/PKG-INFO
py_roku.egg-info/SOURCES.txt
py_roku.egg-info/dependency_links.txt
py_roku.egg-info/requires.txt
py_roku.egg-info/top_level.txt
roku/__init__.py
roku/core.py
roku/discovery.py
roku/proxy.py
roku/server.py
roku/util.py
roku/emulator/__init__.py
roku/emulator/core.py
roku/tests/__init__.py
roku/tests/test_roku.py