Metadata-Version: 1.1
Name: py-roku
Version: 1.1
Summary: Client for the Roku media player
Home-page: https://github.com/villhellm/python-roku
Author: Villhellm
Author-email: will@villhellm.com
License: BSD License
Platform: any
Classifier: Development Status :: 4 - Beta
Classifier: Intended Audience :: Developers
Classifier: License :: OSI Approved :: BSD License
Classifier: Natural Language :: English
Classifier: Operating System :: OS Independent
Classifier: Programming Language :: Python
